turm_gpu-0.0.3.dist-info/METADATA
turm_gpu-0.0.3.dist-info/WHEEL
turm_gpu/__init__.py
turm_gpu/turm_gpu.cpython-312-x86_64-linux-gnu.so
turm_gpu-0.0.3.dist-info/RECORD
