Metadata-Version: 2.3
Name: turm_gpu
Version: 0.0.3
Classifier: Programming Language :: Rust
Classifier: Programming Language :: Python :: Implementation :: CPython
Classifier: Programming Language :: Python :: Implementation :: PyPy
Author: Jiwan Chung <jiwan.chung.research@gmail.com>
Author-email: Jiwan Chung <jiwan.chung.research@gmail.com>
Requires-Python: >=3.8
